teleapi/__init__.py
teleapi/core.py
teleapi-0.1.7.dist-info/LICENSE
teleapi-0.1.7.dist-info/METADATA
teleapi-0.1.7.dist-info/WHEEL
teleapi-0.1.7.dist-info/top_level.txt
teleapi-0.1.7.dist-info/RECORD
