Metadata-Version: 2.1
Name: teleapi
Version: 0.1.7
Summary: Simple telegram api
Home-page: https://github.com/DesSolo/teleapi
Author: DesSolo
Author-email: dessolo@mail.ru
License: BSD
Keywords: telegram bot api
Platform: UNKNOWN
Requires-Python: >=3.5
Requires-Dist: requests
Requires-Dist: pysocks
